cefevent/__init__.py
cefevent/event.py
cefevent/extensions.py
cefevent/generator.py
cefevent/run.py
cefevent/sender.py
cefevent/syslog.py
cefevent/test_event.py
cefevent/test_generator.py
cefevent/test_sender.py
cefevent-0.5.6.dist-info/LICENSE
cefevent-0.5.6.dist-info/METADATA
cefevent-0.5.6.dist-info/WHEEL
cefevent-0.5.6.dist-info/top_level.txt
cefevent-0.5.6.dist-info/RECORD
