Metadata-Version: 2.1
Name: cefevent
Version: 0.5.6
Summary: ArcSight Common Event Format library
Home-page: https://github.com/kamushadenes/cefevent
Download-URL: https://github.com/kamushadenes/cefevent/tarball/0.5.6
Author: Henrique Goncalves
Author-email: kamus@hadenes.io
Keywords: logging,cef,arcsight,event,security
License-File: LICENSE
